MANIFEST.in
README.md
setup.cfg
setup.py
./united_states_of_browsers/usb_server/schema.sql
./united_states_of_browsers/usb_server/static/style.css
./united_states_of_browsers/usb_server/templates/main.html
tests/__init__.py
united_states_of_browsers/__init__.py
united_states_of_browsers/run_usb.py
united_states_of_browsers/db_merge/__init__.py
united_states_of_browsers/db_merge/browser.py
united_states_of_browsers/db_merge/browser_data.py
united_states_of_browsers/db_merge/custom_exceptions.py
united_states_of_browsers/db_merge/db_merge.py
united_states_of_browsers/db_merge/db_search.py
united_states_of_browsers/db_merge/exceptions_handling.py
united_states_of_browsers/db_merge/helpers.py
united_states_of_browsers/db_merge/imported_annotations.py
united_states_of_browsers/db_merge/table.py
united_states_of_browsers/usb_server/__init__.py
united_states_of_browsers/usb_server/usb_server.py
usb.egg-info/PKG-INFO
usb.egg-info/SOURCES.txt
usb.egg-info/dependency_links.txt
usb.egg-info/top_level.txt