Metadata-Version: 2.1
Name: usb
Version: 0.0.83.dev0
Summary: Manage and search browser histories across multiple browsers and browser profiles.
Home-page: https://github.com/kchawla-pi/united-states-of-browsers
Author: kchawla-pi
Author-email: kc.insight.pi@gmail.com
License: UNKNOWN
Keywords: browser history
Platform: UNKNOWN
